espanol/__init__.py
espanol-0.0.1.dist-info/LICENSE
espanol-0.0.1.dist-info/METADATA
espanol-0.0.1.dist-info/WHEEL
espanol-0.0.1.dist-info/top_level.txt
espanol-0.0.1.dist-info/RECORD
