Metadata-Version: 2.1
Name: espanol
Version: 0.0.1
Summary: Espoñol a inglés de Python; Spanish to English for Python
Home-page: https://github.com/TSP66/Espanol
Author: Tom Petty
Author-email: thomas_petty24@student.friends.tas.edu.au
License: UNKNOWN
Project-URL: Bug Tracker, https://github.com/TSP66/Espanol/issues
Platform: UNKNOWN
Classifier: Programming Language :: Python :: 3
Classifier: License :: OSI Approved :: MIT License
Classifier: Operating System :: OS Independent
Requires-Python: >=3.6
License-File: LICENSE
